pytoncenter/__init__.py
pytoncenter/__main__.py
pytoncenter/address.py
pytoncenter/decoder.py
pytoncenter/dispatcher/__init__.py
pytoncenter/exception/__init__.py
pytoncenter/extension/__init__.py
pytoncenter/extension/message.py
pytoncenter/multicall/__init__.py
pytoncenter/requestor/__init__.py
pytoncenter/utils.py
pytoncenter/v2/__init__.py
pytoncenter/v2/api.py
pytoncenter/v2/tools.py
pytoncenter/v2/types.py
pytoncenter/v3/__init__.py
pytoncenter/v3/api.py
pytoncenter/v3/models/__init__.py
pytoncenter/v3/models/customize.py
pytoncenter/v3/models/openapi.py
pytoncenter/v3/models/types.py
pytoncenter-0.0.14.dist-info/LICENSE
pytoncenter-0.0.14.dist-info/METADATA
pytoncenter-0.0.14.dist-info/WHEEL
pytoncenter-0.0.14.dist-info/entry_points.txt
pytoncenter-0.0.14.dist-info/RECORD
