Metadata-Version: 2.1
Name: pytoncenter
Version: 0.0.14
Summary: 
Author: alan890104
Author-email: alan890104@gmail.com
Requires-Python: >=3.9,<3.12
Classifier: Programming Language :: Python :: 3
Classifier: Programming Language :: Python :: 3.9
Classifier: Programming Language :: Python :: 3.10
Classifier: Programming Language :: Python :: 3.11
Requires-Dist: aiohttp (>=3.9.1,<4.0.0)
Requires-Dist: aiolimiter (>=1.1.0,<2.0.0)
Requires-Dist: click (>=8.1.7,<9.0.0)
Requires-Dist: deprecated (>=1.2.14,<2.0.0)
Requires-Dist: pre-commit (>=3.6.1,<4.0.0)
Requires-Dist: pydantic (>=2.5.3,<3.0.0)
Requires-Dist: pyfiglet (>=1.0.2,<2.0.0)
Requires-Dist: pynacl (>=1.5.0,<2.0.0)
Requires-Dist: tonpy (>=0.0.0.1.2b0,<0.0.1.0.0)
Requires-Dist: treelib (>=1.7.0,<2.0.0)
